Imager/__init__.py
Imager-0.1.dist-info/LICENSE.txt
Imager-0.1.dist-info/METADATA
Imager-0.1.dist-info/WHEEL
Imager-0.1.dist-info/top_level.txt
Imager-0.1.dist-info/RECORD
