Metadata-Version: 2.1
Name: Imager
Version: 0.1
Summary: A Image Finder Search Engine.
Home-page: https://github.com/MuhammadHananAsghar
Author: Muhammad Hanan Asghar
Author-email: muhammadhananasghar@gamil.com
License: UNKNOWN
Platform: UNKNOWN
Classifier: Programming Language :: Python :: 3
Classifier: License :: OSI Approved :: MIT License
Classifier: Operating System :: OS Independent
Requires-Dist: bs4
Requires-Dist: requests
Requires-Dist: wheel
